mdspy/PCA_timeseries.py
mdspy/__init__.py
mdspy/analytics.py
mdspy/anomaly_detection.py
mdspy/cache_queries.py
mdspy/data_creation.py
mdspy/features.py
mdspy/spark.py
mdspy/time_tools.py
mdspy/ttt.py
mdspy-1.0.18.dist-info/LICENSE
mdspy-1.0.18.dist-info/METADATA
mdspy-1.0.18.dist-info/WHEEL
mdspy-1.0.18.dist-info/top_level.txt
mdspy-1.0.18.dist-info/RECORD
