Metadata-Version: 2.1
Name: mdspy
Version: 1.0.18
Summary: Mnubo Data Science Library
Home-page: UNKNOWN
Author: mnubo, inc.
Author-email: support@mnubo.com
License: UNKNOWN
Keywords: mnubo,iot,smartobjects
Platform: UNKNOWN
Classifier: Operating System :: OS Independent
Classifier: Programming Language :: Python
Requires-Dist: nose (==1.3.7)
Requires-Dist: sphinx (==1.7.6)
Requires-Dist: numpy (==1.15.3)
Requires-Dist: scipy (==1.1.0)
Requires-Dist: pandas (==0.23.4)
Requires-Dist: scikit-learn (==0.20.2)
Requires-Dist: setuptools (==39.2.0)
Requires-Dist: matplotlib (==2.2.2)
Requires-Dist: seaborn (==0.9.0)
Requires-Dist: statsmodels (==0.8.0)
Requires-Dist: aiot-studio (==1.0.20)
Requires-Dist: fastparquet (==0.1.6)
Requires-Dist: sphinx-rtd-theme (==0.4.1)
Requires-Dist: numpydoc (==0.8.0)
Requires-Dist: unittest2 (==1.1.0)
Requires-Dist: pyspark (==2.3.1)
